mfi_mpower/__init__.py
mfi_mpower/device.py
mfi_mpower/entities.py
mfi_mpower/enums.py
mfi_mpower/exceptions.py
mfi_mpower/interface.py
mfi_mpower/parsers.py
mfi_mpower/session.py
mfi_mpower-3.2.2.dist-info/licenses/LICENSE
mfi_mpower-3.2.2.dist-info/METADATA
mfi_mpower-3.2.2.dist-info/WHEEL
mfi_mpower-3.2.2.dist-info/top_level.txt
mfi_mpower-3.2.2.dist-info/RECORD
