Metadata-Version: 2.4
Name: mfi-mpower
Version: 3.2.2
Summary: Asynchronous Python API for mFi mPower devices
Author-email: pasbec <p.b-dev+mfi-mpower@mailbox.org>
License: MIT License
Project-URL: Homepage, https://github.com/pasbec/mfi
Keywords: ubiquiti,mfi,mpower
Platform: any
Classifier: License :: OSI Approved :: MIT License
Classifier: Programming Language :: Python
Classifier: Programming Language :: Python :: 3
Requires-Python: >=3.9
License-File: LICENSE
Requires-Dist: asyncssh
Provides-Extra: dev
Requires-Dist: black; extra == "dev"
Requires-Dist: build; extra == "dev"
Requires-Dist: bump-my-version; extra == "dev"
Requires-Dist: isort; extra == "dev"
Requires-Dist: pip-tools; extra == "dev"
Requires-Dist: pylint; extra == "dev"
Requires-Dist: pytest; extra == "dev"
Requires-Dist: twine; extra == "dev"
Requires-Dist: wheel; extra == "dev"
Dynamic: license-file
